imdb/__init__.py
imdb/__main__.py
imdb/api.py
imdb/imdb.py
tdmc-0.1.1.dist-info/LICENSE
tdmc-0.1.1.dist-info/METADATA
tdmc-0.1.1.dist-info/WHEEL
tdmc-0.1.1.dist-info/entry_points.txt
tdmc-0.1.1.dist-info/top_level.txt
tdmc-0.1.1.dist-info/RECORD
