Metadata-Version: 2.1
Name: tdmc
Version: 0.1.1
Summary: Get imdb ratings.
Author-email: Matthew Chan <chan320@purdue.edu>
License: MIT License
Keywords: example,imdb,tutorial
Classifier: License :: OSI Approved :: MIT License
Classifier: Programming Language :: Python
Classifier: Programming Language :: Python :: 3
Classifier: Development Status :: 2 - Pre-Alpha
Requires-Python: >=3.10
License-File: LICENSE
Requires-Dist: lxml (>=4.9.1)
Requires-Dist: requests (>=2.28.1)
Requires-Dist: fastapi (>=0.85.2)
Requires-Dist: Jinja2 (>=3.1.2)
Requires-Dist: uvicorn[standard]
